Metadata-Version: 2.1
Name: compExtract
Version: 0.0.9
Summary: Extract keywords via comparison of corpus
Home-page: https://github.com/ALaughingHorse/comparative_keyword_extraction
Author: Xiao Ma
Author-email: Marshalma0923@gmail.com
License: MIT
Download-URL: https://github.com/ALaughingHorse/comparative_keyword_extraction/archive/v_009.tar.gz
Keywords: NLP
Platform: UNKNOWN
Classifier: Development Status :: 3 - Alpha
Classifier: Intended Audience :: Developers
Classifier: Topic :: Software Development :: Build Tools
Classifier: License :: OSI Approved :: MIT License
Classifier: Programming Language :: Python :: 3
Classifier: Programming Language :: Python :: 3.4
Classifier: Programming Language :: Python :: 3.5
Classifier: Programming Language :: Python :: 3.6
Classifier: Programming Language :: Python :: 3.7
License-File: LICENSE.txt
